__init__.py
common.py
execute.py
library.py
AssemblyLinePython-0.0.2.dist-info/METADATA
AssemblyLinePython-0.0.2.dist-info/WHEEL
AssemblyLinePython-0.0.2.dist-info/top_level.txt
AssemblyLinePython-0.0.2.dist-info/RECORD
