Metadata-Version: 2.1
Name: AssemblyLinePython
Version: 0.0.2
Summary: TODO
Home-page: https://github.com/FloydZ/AssemblyLinePython
Author: Floyd Zweydinger
Author-email: zweydfg8+github@rub.de
Keywords: assembly,assembler,asm,opcodes,x86,x86-64,isa,cpu
Classifier: Development Status :: 4 - Beta
Classifier: Intended Audience :: Developers
Classifier: Intended Audience :: Science/Research
Classifier: Operating System :: OS Independent
Classifier: Programming Language :: Assembly
Classifier: Programming Language :: Python
Classifier: Programming Language :: Python :: 3
Classifier: Topic :: Scientific/Engineering
Classifier: Topic :: Software Development
Classifier: Topic :: Software Development :: Assemblers
Classifier: Topic :: Software Development :: Documentation
Requires-Dist: setuptools
